vcgencmd/__init__.py
vcgencmd/__main__.py
vcgencmd/vcgencmd.py
vcgencmd-0.1.1.dist-info/LICENSE
vcgencmd-0.1.1.dist-info/METADATA
vcgencmd-0.1.1.dist-info/WHEEL
vcgencmd-0.1.1.dist-info/top_level.txt
vcgencmd-0.1.1.dist-info/RECORD
