Metadata-Version: 2.1
Name: vcgencmd
Version: 0.1.1
Summary: Python binding for RaspberryPi vcgencmd command-line tool
Home-page: https://github.com/sushantnadkar/vcgencmd.git
Author: Sushant Nadkar
License: The MIT License (MIT)
Platform: UNKNOWN
Classifier: Programming Language :: Python :: 3
Classifier: License :: OSI Approved :: MIT License
